LICENSE
MANIFEST.in
README.rst
setup.py
doc/Makefile
doc/changelog.rst
doc/classes.rst
doc/conf.py
doc/faq.rst
doc/index.rst
doc/_static/toro.png
doc/examples/event_example.rst
doc/examples/index.rst
doc/examples/lock_example.rst
doc/examples/producer_consumer_example.rst
doc/examples/web_spider_example.rst
examples/__init__.py
examples/event_example.py
examples/lock_example.py
examples/producer_consumer_example.py
examples/web_spider_example.py
test/__init__.py
test/test_async_result.py
test/test_condition.py
test/test_event.py
test/test_lock.py
test/test_queue.py
test/test_rwlock.py
test/test_semaphore.py
test/test_timeout.py
toro/__init__.py
toro.egg-info/PKG-INFO
toro.egg-info/SOURCES.txt
toro.egg-info/dependency_links.txt
toro.egg-info/requires.txt
toro.egg-info/top_level.txt