Metadata-Version: 1.1
Name: toro
Version: 1.0.1
Summary: Synchronization primitives for Tornado coroutines.
Home-page: http://github.com/ajdavis/toro/
Author: A. Jesse Jiryu Davis
Author-email: jesse@emptysquare.net
License: http://www.apache.org/licenses/LICENSE-2.0
Keywords: tornado coroutines semaphore mutex queue asynchronous
Platform: UNKNOWN
Classifier: Intended Audience :: Developers
Classifier: License :: OSI Approved :: Apache Software License
Classifier: Development Status :: 4 - Beta
Classifier: Natural Language :: English
Classifier: Programming Language :: Python :: 2
Classifier: Programming Language :: Python :: 2.6
Classifier: Programming Language :: Python :: 2.7
Classifier: Programming Language :: Python :: 3
Classifier: Programming Language :: Python :: 3.2
Classifier: Programming Language :: Python :: 3.3
Classifier: Programming Language :: Python :: 3.4
Classifier: Operating System :: MacOS :: MacOS X
Classifier: Operating System :: Unix
Classifier: Programming Language :: Python
Classifier: Programming Language :: Python :: Implementation :: CPython
Classifier: Programming Language :: Python :: Implementation :: PyPy
